{
  "set_num": "21330",
  "pdf_name": "21330_01",
  "labels": {
    "13": "true_bag_start",
    "28": "true_bag_start",
    "77": "true_bag_start",
    "86": "sticker_or_callout",
    "88": "true_bag_start",
    "104": "normal_step",
    "110": "sticker_or_callout",
    "120": "sticker_or_callout",
    "127": "true_bag_start",
    "137": "normal_step",
    "150": "true_bag_start",
    "158": "normal_step",
    "161": "normal_step",
    "164": "normal_step",
    "178": "normal_step",
    "181": "normal_step",
    "189": "normal_step",
    "192": "normal_step",
    "195": "true_bag_start",
    "199": "normal_step",
    "205": "normal_step",
    "210": "true_bag_start",
    "214": "true_bag_start",
    "215": "normal_step",
    "220": "sticker_or_callout",
    "230": "true_bag_start",
    "237": "sticker_or_callout",
    "252": "true_bag_start",
    "264": "true_bag_start",
    "277": "true_bag_start",
    "290": "normal_step",
    "291": "normal_step",
    "298": "true_bag_start",
    "316": "true_bag_start",
    "332": "true_bag_start",
    "349": "true_bag_start",
    "367": "normal_step",
    "372": "normal_step",
    "373": "true_bag_start",
    "381": "normal_step",
    "391": "true_bag_start",
    "406": "true_bag_start",
    "407": "sticker_or_callout",
    "433": "true_bag_start"
  },
  "unsure_pages": [
    "1",
    "2",
    "3",
    "4",
    "5",
    "6",
    "7",
    "8",
    "9",
    "10",
    "11",
    "12",
    "14",
    "462",
    "463",
    "467",
    "468",
    "469"
  ]
}